setup.py
ghost_translator/__init__.py
ghost_translator.egg-info/PKG-INFO
ghost_translator.egg-info/SOURCES.txt
ghost_translator.egg-info/dependency_links.txt
ghost_translator.egg-info/entry_points.txt
ghost_translator.egg-info/requires.txt
ghost_translator.egg-info/top_level.txt