Metadata-Version: 1.1
Name: ghost-translator
Version: 1.0.0
Summary: Finds translatable fields in your ghost theme and updates locale files.
Home-page: https://github.com/arthurnoerve/ghost-translator
Author: arthurnoerve
Author-email: arthur@avgar.de
License: UNKNOWN
Keywords: ghost translate handlebars
Platform: UNKNOWN
Classifier: Development Status :: 5 - Production/Stable
Classifier: Intended Audience :: Developers
Classifier: Topic :: Software Development :: Build Tools
Classifier: License :: OSI Approved :: MIT License
Classifier: Programming Language :: Python :: 2
Classifier: Programming Language :: Python :: 2.6
Classifier: Programming Language :: Python :: 3
Classifier: Programming Language :: Python :: 3.4
Classifier: Programming Language :: Python :: 3.5
Classifier: Programming Language :: Python :: 3.6
